yc_django_utils/__init__.py
yc_django_utils/core_initialize.py
yc_django_utils/crud_mixin.py
yc_django_utils/exception.py
yc_django_utils/filters.py
yc_django_utils/import_export.py
yc_django_utils/import_export_mixin.py
yc_django_utils/json_response.py
yc_django_utils/middleware.py
yc_django_utils/models.py
yc_django_utils/pagination.py
yc_django_utils/request_util.py
yc_django_utils/send_mail.py
yc_django_utils/serializers.py
yc_django_utils/string_util.py
yc_django_utils/validator.py
yc_django_utils/viewset.py
yc_django_utils-0.0.7.dist-info/LICENSE
yc_django_utils-0.0.7.dist-info/METADATA
yc_django_utils-0.0.7.dist-info/WHEEL
yc_django_utils-0.0.7.dist-info/top_level.txt
yc_django_utils-0.0.7.dist-info/RECORD
